publikstemku/Stem.py
publikstemku/__init__.py
publikstemku-0.1.dist-info/METADATA
publikstemku-0.1.dist-info/WHEEL
publikstemku-0.1.dist-info/top_level.txt
publikstemku-0.1.dist-info/RECORD
