Metadata-Version: 2.1
Name: publikstemku
Version: 0.1
Requires-Dist: mysql-connector-python >=8.1.0
